{
  "menu": [
    {
      "img": "img/tabs/vegy.jpg",
      "alt": "vegy",
      "title": "Меню 'Фитнес'",
      "text": "Меню 'Фитнес' - это новый подход к приготовлению блюд: больше свежих овощей и фруктов. Продукт активных и здоровых людей. Это абсолютно новый продукт с оптимальной ценой и высоким качеством!",
      "price": 9,
      "id": "6663"
    },
    {
      "img": "img/tabs/post.jpg",
      "alt": "post",
      "title": "Меню 'Постное'",
      "text": "Меню 'Постное' - это тщательный подбор ингредиентов: полное отсутствие продуктов животного происхождения, молоко из миндаля, овса, кокоса или гречки, правильное количество белков за счет тофу и импортных вегетарианских стейков.",
      "price": 14,
      "id": "8718"
    },
    {
      "img": "img/tabs/elite.jpg",
      "alt": "elite",
      "title": "Меню 'Премиум'",
      "text": "В меню “Премиум” не только привлекательный дизайн упаковки, но и качественное исполнение блюд. Красная рыба, морепродукты, фрукты — меню, позволяющее насладиться изысканным ужином, не выходя из дома!",
      "price": 21,
      "id": "f294"
    }
  ],
  "requests": [
    {
      "id": "e52a",
      "name": "tim",
      "phone": "+74949493030"
    },
    {
      "id": "46aa",
      "name": "test",
      "phone": "+994508786890"
    }
  ]
}